telnetlib_proxy/__init__.py
telnetlib_proxy-0.3.dist-info/LICENSE
telnetlib_proxy-0.3.dist-info/METADATA
telnetlib_proxy-0.3.dist-info/WHEEL
telnetlib_proxy-0.3.dist-info/entry_points.txt
telnetlib_proxy-0.3.dist-info/top_level.txt
telnetlib_proxy-0.3.dist-info/RECORD
